{
    "uuid": [
        {
            "value": "d40b6ade-6ce6-4744-8c16-3d5f90a04a61"
        }
    ],
    "langcode": [
        {
            "value": "en"
        }
    ],
    "uid": [],
    "filename": [
        {
            "value": "victoria-sponge-umami.jpg"
        }
    ],
    "uri": [
        {
            "value": "public:\/\/victoria-sponge-umami.jpg"
        }
    ],
    "filemime": [
        {
            "value": "image\/jpeg"
        }
    ],
    "filesize": [
        {
            "value": 65418
        }
    ],
    "status": [
        {
            "value": true
        }
    ],
    "created": [
        {
            "value": "2019-03-01T14:14:29+00:00",
            "format": "Y-m-d\\TH:i:sP"
        }
    ],
    "changed": [
        {
            "value": "2019-03-01T14:14:29+00:00",
            "format": "Y-m-d\\TH:i:sP"
        }
    ]
}